LICENSE
README.md
setup.py
apkinjector/__init__.py
apkinjector/__main__.py
apkinjector/adb.py
apkinjector/apktool.py
apkinjector/arch.py
apkinjector/bundle.py
apkinjector/dependencies.py
apkinjector/download.py
apkinjector/frida.py
apkinjector/gadget.py
apkinjector/injector.py
apkinjector/java.py
apkinjector/logger.py
apkinjector/manifest.py
apkinjector/plugins.py
apkinjector/uber_apk_signer.py
apkinjector/utils.py
apkinjector.egg-info/PKG-INFO
apkinjector.egg-info/SOURCES.txt
apkinjector.egg-info/dependency_links.txt
apkinjector.egg-info/entry_points.txt
apkinjector.egg-info/requires.txt
apkinjector.egg-info/top_level.txt