Metadata-Version: 2.1
Name: apkinjector
Version: 1.1.6
Summary: Utilities to help injecting libraries and frida in apks.
Home-page: https://nitanmarcel.github.io/apkinjector
Author: Marcel Alexandru Nitan
Author-email: nitan.marcel@gmail.com
Keywords: FRIDA,APK,INJECTION,INJECT
Classifier: License :: OSI Approved :: GNU General Public License v2 (GPLv2)
Classifier: Programming Language :: Python :: 3.6
Classifier: Programming Language :: Python :: 3.7
Classifier: Programming Language :: Python :: 3.8
Classifier: Programming Language :: Python :: 3.9
Classifier: Programming Language :: Python :: 3.10
Classifier: Programming Language :: Python :: 3.11
License-File: LICENSE
